{"type":"FeatureCollection","features":[{"type":"Feature","properties":{"fulcrum_id":"df97f080-22a2-4829-9bc7-b8c77f6e3a66","created_at":"2014-05-02 15:18:17 UTC","updated_at":"2014-05-02 15:27:38 UTC","created_by":"cjseeger@gmail.com","updated_by":"cjseeger@gmail.com","system_created_at":"2014-05-02 15:19:11 UTC","system_updated_at":"2014-05-02 15:27:43 UTC","version":2,"status":null,"project":null,"assigned_to":null,"latitude":42.0211662460561,"longitude":-93.6184712871909,"feature":"Additional Feature","sidewalks_midblock":null,"sidewalk_condition":null,"sidewalk_width":null,"sidewalk_set_back":null,"parking":null,"pleasant":null,"why_not_pleasant":null,"street_light":null,"bike_lanes":null,"additional_features":null,"additional_features_other":"Jerk","elementary_safe":null,"why_not_street":null,"do_you_think_an_adult_would_feel_safe_crossing_this_street":null,"conditions":null,"streets_intersect":null,"traffic_controlled":null,"traffic_controlled_other":null,"pedestrian_signage":null,"pedestrian_signage_other":null,"crossing_guard":null,"curb_cuts":null,"curbcut_condition":null,"painted_crosswalks":null,"road_too_wide":null,"time_to_cross":null,"difficult_traffic_to_see":null,"describe_conditions":null,"comment":"Test","photos":"5E034AF2-F91F-4FBF-8C14-C8ADE3332EF5,ADEC737C-7BC1-494A-A7CD-2900F3FF784D","photos_caption":","},"geometry":{"type":"Point","coordinates":[-93.6184712871909,42.0211662460561]}}]}